compiler_config/__init__.py
compiler_config/config.py
compiler_config/serialiser.py
compiler_config-0.2.0.dist-info/LICENSE
compiler_config-0.2.0.dist-info/METADATA
compiler_config-0.2.0.dist-info/WHEEL
compiler_config-0.2.0.dist-info/entry_points.txt
compiler_config-0.2.0.dist-info/RECORD
